dynagrpc/__init__.py
dynagrpc/_astcast.py
dynagrpc-0.1.0.dist-info/LICENSE.txt
dynagrpc-0.1.0.dist-info/WHEEL
dynagrpc-0.1.0.dist-info/METADATA
dynagrpc-0.1.0.dist-info/RECORD
