Metadata-Version: 2.1
Name: dynagrpc
Version: 0.1.0
Summary: DynagRPC Python abstraction library over gRPC and protobuf types.
Requires-Python: >=3.7
Classifier: Intended Audience :: Developers
Classifier: License :: OSI Approved :: Apache Software License
Classifier: Operating System :: OS Independent
Requires-Dist: grpcio-tools
Requires-Dist: protobuf
Requires-Dist: typing_extensions;python_version=='3.7'
Project-URL: Home, https://github.com/danilobellini/dynagrpc
